CHANGES.txt
MANIFEST.in
README.txt
setup.py
src/rsl/__init__.py
src/rsl.http.egg-info/PKG-INFO
src/rsl.http.egg-info/SOURCES.txt
src/rsl.http.egg-info/dependency_links.txt
src/rsl.http.egg-info/entry_points.txt
src/rsl.http.egg-info/namespace_packages.txt
src/rsl.http.egg-info/requires.txt
src/rsl.http.egg-info/top_level.txt
src/rsl/http/__init__.py
src/rsl/http/factories.py
src/rsl/http/namespace.py
src/rsl/http/proxy.py
src/rsl/http/proxy_flymake.py
src/rsl/http/schema.py
src/rsl/http/serializer.py
src/rsl/http/wsdl1.py
src/rsl/http/xsds/wsdlhttp.xsd